{
  "home": "Home",
  "title1": "Discover and book your favorite events",
  "title2": "Concerts, festivals, conferences, shows... Find and book your tickets online in just a few clicks. Live unforgettable experiences with our platform!",
  "event": "Event",
  "event-title": "Find and book your tickets",

  "loading": "Loading...",
  "no_events": "No events available.",
  "unknown_speaker": "Unknown speaker",


  "please_log_in_to_view": "Please log in to view the events",



  "nav_home": "Home",
  "nav_event": "Events",
  "nav_users": "User Management",
  "nav_events": "Event Management",
  "nav_tickets": "Ticket Management",
  "open_menu": "Open menu",
  "logout": "Logout",
  "register": "Sign Up",
  "login": "Login",

  "add-event" : "add event",
  "add-user" : "add user",
  "title-profile" : "Change your personal information.",


  "profile": {
    "title": "Profile",
    "date-create-profile": "Creation date",
    "name": "Name",
    "email": "Email",
    "password": "New Password",
    "save": "Save",
    "cancel": "Cancel",
    "edit": "Edit",
    "no_user_info": "No user information found."
  },

  "tickets": {
    "title": "My Tickets",
    "description": "Find all your tickets here.",
    "loading": "Loading tickets...",
    "no_tickets": "No tickets found.",
    "ticket_number": "Ticket #",
    "event_name": "Event name",
    "price": "Price",
    "created_at": "Created on",
    "delete": "Delete",
    "status" : "Status",
    "purchase_date" : "Purchase date",
    "add" : "Add Ticket",
    "validate" : "Validate"
  },

  "users": {
    "title":"Users"
  }

}
